k7eel/__init__.py
k7eel/main.py
k7eel-0.1.3.dist-info/METADATA
k7eel-0.1.3.dist-info/WHEEL
k7eel-0.1.3.dist-info/entry_points.txt
k7eel-0.1.3.dist-info/top_level.txt
k7eel-0.1.3.dist-info/RECORD
